{
  "DOT-Polkadot": {
    "slug": "DOT-Polkadot",
    "originChainAsset": "polkadot-NATIVE-DOT",
    "name": "Polkadot",
    "symbol": "DOT",
    "priceId": "polkadot",
    "hasValue": true
  },
  "KSM-Kusama": {
    "slug": "KSM-Kusama",
    "originChainAsset": "kusama-NATIVE-KSM",
    "name": "Kusama",
    "symbol": "KSM",
    "priceId": "kusama",
    "hasValue": true
  },
  "GLMR-Moonbeam": {
    "slug": "GLMR-Moonbeam",
    "originChainAsset": "moonbeam-NATIVE-GLMR",
    "name": "Moonbeam",
    "symbol": "GLMR",
    "priceId": "moonbeam",
    "hasValue": true
  },
  "ACA-Acala": {
    "slug": "ACA-Acala",
    "originChainAsset": "acala-NATIVE-ACA",
    "name": "Acala",
    "symbol": "ACA",
    "priceId": "acala",
    "hasValue": true
  },
  "KAR-Karura": {
    "slug": "KAR-Karura",
    "originChainAsset": "karura-NATIVE-KAR",
    "name": "Karura",
    "symbol": "KAR",
    "priceId": "karura",
    "hasValue": true
  },
  "USDT-Tether": {
    "slug": "USDT-Tether",
    "originChainAsset": null,
    "name": "Tether",
    "symbol": "USDT",
    "priceId": "tether",
    "hasValue": true
  },
  "ETH-Ethereum": {
    "slug": "ETH-Ethereum",
    "originChainAsset": "ethereum-NATIVE-ETH",
    "name": "Ethereum",
    "symbol": "ETH",
    "priceId": "ethereum",
    "hasValue": true
  },
  "ASTR-Astar": {
    "slug": "ASTR-Astar",
    "originChainAsset": "astar-NATIVE-ASTR",
    "name": "Astar",
    "symbol": "ASTR",
    "priceId": "astar",
    "hasValue": true
  },
  "aUSD-AcalaDollar": {
    "slug": "aUSD-AcalaDollar",
    "originChainAsset": null,
    "name": "Acala Dollar",
    "symbol": "aUSD",
    "priceId": "acala-dollar-acala",
    "hasValue": true
  },
  "aUSD-KaruraDollar": {
    "slug": "aUSD-KaruraDollar",
    "originChainAsset": null,
    "name": "Karura Dollar",
    "symbol": "aUSD",
    "priceId": "acala-dollar",
    "hasValue": true
  },
  "DEV-MoonbaseDev": {
    "slug": "DEV-MoonbaseDev",
    "originChainAsset": "moonbase-NATIVE-DEV",
    "name": "Moonbase Dev",
    "symbol": "DEV",
    "priceId": null,
    "hasValue": false
  },
  "MOVR-Moonriver": {
    "slug": "MOVR-Moonriver",
    "originChainAsset": "moonriver-NATIVE-MOVR",
    "name": "Moonriver",
    "symbol": "MOVR",
    "priceId": "moonriver",
    "hasValue": true
  },
  "BNC-BifrostKusama": {
    "slug": "BNC-BifrostKusama",
    "originChainAsset": "bifrost-NATIVE-BNC",
    "name": "Bifrost Kusama",
    "symbol": "BNC",
    "priceId": "bifrost-native-coin",
    "hasValue": true
  },
  "NEER-Pioneer": {
    "slug": "NEER-Pioneer",
    "originChainAsset": "pioneer-NATIVE-NEER",
    "name": "Pioneer",
    "symbol": "NEER",
    "priceId": "metaverse-network-pioneer",
    "hasValue": true
  },
  "INTR-Interlay": {
    "slug": "INTR-Interlay",
    "originChainAsset": "interlay-NATIVE-INTR",
    "name": "Interlay",
    "symbol": "INTR",
    "priceId": "interlay",
    "hasValue": true
  },
  "iBTC-interBTC": {
    "slug": "iBTC-interBTC",
    "originChainAsset": "interlay-LOCAL-iBTC",
    "name": "interBTC",
    "symbol": "iBTC",
    "priceId": "interbtc",
    "hasValue": true
  },
  "KINT-Kintsugi": {
    "slug": "KINT-Kintsugi",
    "originChainAsset": "kintsugi-NATIVE-KINT",
    "name": "Kintsugi",
    "symbol": "KINT",
    "priceId": "kintsugi",
    "hasValue": true
  },
  "kBTC-KintsugiWrappedBTC": {
    "slug": "kBTC-KintsugiWrappedBTC",
    "originChainAsset": "kintsugi-LOCAL-kBTC",
    "name": "Kintsugi Wrapped BTC",
    "symbol": "kBTC",
    "priceId": "kintsugi-btc",
    "hasValue": true
  },
  "USDC-USDCoin": {
    "slug": "USDC-USDCoin",
    "originChainAsset": null,
    "name": "USDC",
    "symbol": "USDC",
    "priceId": "usd-coin",
    "hasValue": true
  },
  "BNB-Binance": {
    "slug": "BNB-Binance",
    "originChainAsset": "binance-NATIVE-BNB",
    "name": "Binance Smart Chain",
    "symbol": "BNB",
    "priceId": "binancecoin",
    "hasValue": true
  },
  "BUSD-BinanceUSD": {
    "slug": "BUSD-BinanceUSD",
    "originChainAsset": "binance-ERC20-BUSD-0xe9e7cea3dedca5984780bafc599bd69add087d56",
    "name": "Binance USD",
    "symbol": "BUSD",
    "priceId": "binance-usd",
    "hasValue": true
  },
  "DAI-DaiStablecoin": {
    "slug": "DAI-DaiStablecoin",
    "originChainAsset": null,
    "name": "Dai Stablecoin",
    "symbol": "DAI",
    "priceId": "dai",
    "hasValue": true
  },
  "SDN-Shiden": {
    "slug": "SDN-Shiden",
    "originChainAsset": "shiden-NATIVE-SDN",
    "name": "Shiden",
    "symbol": "SDN",
    "priceId": "shiden",
    "hasValue": true
  },
  "PKEX-PolkaEx": {
    "slug": "PKEX-PolkaEx",
    "originChainAsset": null,
    "name": "PolkaEx",
    "symbol": "PKEX",
    "priceId": "polkaex",
    "hasValue": true
  },
  "CRU-Crust": {
    "slug": "CRU-Crust",
    "originChainAsset": "crust-NATIVE-CRU",
    "name": "Crust",
    "symbol": "CRU",
    "priceId": "crust-network",
    "hasValue": true
  },
  "PHA-Phala": {
    "slug": "PHA-Phala",
    "originChainAsset": "phala-NATIVE-PHA",
    "name": "Phala",
    "symbol": "PHA",
    "priceId": "pha",
    "hasValue": true
  },
  "PARA-Parallel": {
    "slug": "PARA-Parallel",
    "originChainAsset": "parallel-NATIVE-PARA",
    "name": "Parallel",
    "symbol": "PARA",
    "priceId": "parallel-finance",
    "hasValue": true
  },
  "BOBA-BobaToken": {
    "slug": "BOBA-BobaToken",
    "originChainAsset": "bobabeam-NATIVE-BOBA",
    "name": "Boba Token",
    "symbol": "BOBA",
    "priceId": "boba-network",
    "hasValue": true
  },
  "EQD-EquilibriumUSD": {
    "slug": "EQD-EquilibriumUSD",
    "originChainAsset": "equilibrium_parachain-LOCAL-EQD",
    "name": "Equilibrium USD",
    "symbol": "EQD",
    "priceId": null,
    "hasValue": true
  },
  "WETH-WrappedEther": {
    "slug": "WETH-WrappedEther",
    "originChainAsset": "ethereum-ERC20-WETH-0xc02aaa39b223fe8d0a0e5c4f27ead9083c756cc2",
    "name": "Wrapped Ether",
    "symbol": "WETH",
    "priceId": "weth",
    "hasValue": true
  },
  "RMRK-RMRKApp": {
    "slug": "RMRK-RMRKApp",
    "originChainAsset": "statemine-LOCAL-RMRK",
    "name": "RMRK.app",
    "symbol": "RMRK",
    "priceId": "rmrk",
    "hasValue": true
  },
  "WBTC-WrappedBTC": {
    "slug": "WBTC-WrappedBTC",
    "originChainAsset": null,
    "name": "Wrapped BTC",
    "symbol": "WBTC",
    "priceId": "wrapped-bitcoin",
    "hasValue": true
  },
  "MATIC-Polygon": {
    "slug": "MATIC-Polygon",
    "originChainAsset": "polygon-NATIVE-MATIC",
    "name": "Polygon",
    "symbol": "MATIC",
    "priceId": "matic-network",
    "hasValue": true
  },
  "ARB-ArbitrumOne": {
    "slug": "ARB-ArbitrumOne",
    "originChainAsset": "arbitrum_one-ERC20-ARB-0x912CE59144191C1204E64559FE8253a0e49E6548",
    "name": "Arbitrum One",
    "symbol": "ARB",
    "priceId": "arbitrum",
    "hasValue": true
  },
  "OP-Optimism": {
    "slug": "OP-Optimism",
    "originChainAsset": "optimism-ERC20-OP-0x4200000000000000000000000000000000000042",
    "name": "Optimism",
    "symbol": "OP",
    "priceId": "optimism",
    "hasValue": true
  },
  "EQ-Equilibrium": {
    "slug": "EQ-Equilibrium",
    "originChainAsset": "equilibrium_parachain-NATIVE-EQ",
    "name": "Equilibrium",
    "symbol": "EQ",
    "priceId": "equilibrium-token",
    "hasValue": true
  },
  "KMA-Calamari": {
    "slug": "KMA-Calamari",
    "originChainAsset": "calamari-NATIVE-KMA",
    "name": "Calamari",
    "symbol": "KMA",
    "priceId": "calamari-network",
    "hasValue": true
  },
  "FTM-Fantom": {
    "slug": "FTM-Fantom",
    "originChainAsset": "fantom-NATIVE-FTM",
    "name": "Fantom",
    "symbol": "FTM",
    "priceId": "fantom",
    "hasValue": true
  },
  "aSEED-aSEEDAcala": {
    "slug": "aSEED-aSEEDAcala",
    "originChainAsset": "acala-LOCAL-aSEED",
    "name": "aUSD SEED (Acala)",
    "symbol": "aSEED",
    "priceId": "ausd-seed-acala",
    "hasValue": true
  },
  "aSEED-aSEEDKarura": {
    "slug": "aSEED-aSEEDKarura",
    "originChainAsset": "karura-LOCAL-aSEED",
    "name": "aUSD SEED (Karura)",
    "symbol": "aSEED",
    "priceId": "ausd-seed-karura",
    "hasValue": true
  },
  "DPR-DeeperNetwork": {
    "slug": "DPR-DeeperNetwork",
    "originChainAsset": "ethereum-ERC20-DPR-0xf3AE5d769e153Ef72b4e3591aC004E89F48107a1",
    "name": "Deeper Network",
    "symbol": "DPR",
    "priceId": "deeper-network",
    "hasValue": true
  },
  "USDD-DecentralizedUSD": {
    "slug": "USDD-DecentralizedUSD",
    "originChainAsset": null,
    "name": "Decentralized USD",
    "symbol": "USDD",
    "priceId": "usdd",
    "hasValue": true
  }
}
